memoreka/__init__.py
memoreka/error.py
memoreka-0.2.24.2.dist-info/LICENSE
memoreka-0.2.24.2.dist-info/METADATA
memoreka-0.2.24.2.dist-info/WHEEL
memoreka-0.2.24.2.dist-info/top_level.txt
memoreka-0.2.24.2.dist-info/RECORD
