Metadata-Version: 2.1
Name: memoreka
Version: 0.2.24.2
Summary: 秒花笔记API
Home-page: https://github.com/daizihan233/memoreka
Author: KuoHu
Author-email: hantools@foxmail.com
Classifier: Programming Language :: Python :: 3
Classifier: License :: OSI Approved :: MIT License
Classifier: Operating System :: OS Independent
License-File: LICENSE
Requires-Dist: requests
